pyfirmata2/__init__.py
pyfirmata2/boards.py
pyfirmata2/mockup.py
pyfirmata2/pyfirmata2.py
pyfirmata2/util.py
pyFirmata2-2.5.1.dist-info/LICENSE
pyFirmata2-2.5.1.dist-info/METADATA
pyFirmata2-2.5.1.dist-info/WHEEL
pyFirmata2-2.5.1.dist-info/top_level.txt
pyFirmata2-2.5.1.dist-info/RECORD
