Metadata-Version: 2.1
Name: pyFirmata2
Version: 2.5.1
Summary: Use your Arduino as a data acquisition card under Python
Home-page: https://github.com/berndporr/pyFirmata2
Author: Bernd Porr
Author-email: mail@berndporr.me.uk
Classifier: Intended Audience :: Developers
Classifier: License :: OSI Approved :: MIT License
Classifier: Operating System :: OS Independent
Classifier: Programming Language :: Python :: 3
Classifier: Topic :: Utilities
License-File: LICENSE
